pkgtest/__init__.py
pkgtest/test.py
retection/__init__.py
retection/test.py
retection-0.0.2.dist-info/METADATA
retection-0.0.2.dist-info/WHEEL
retection-0.0.2.dist-info/top_level.txt
retection-0.0.2.dist-info/RECORD
