Metadata-Version: 2.1
Name: retection
Version: 0.0.2
Summary: retection Test
Home-page: https://github.com/5hale/retection
Author: 5hale
Author-email: sekunrity@gmail.com
License: UNKNOWN
Platform: UNKNOWN
Requires-Python: >=3
